chembioml/LinearRidgeGATrainer.py
chembioml/LinearRidgePredictor.py
chembioml/__init__.py
chembioml/cli.py
chembioml/utils.py
chembioml-0.1.0.dist-info/METADATA
chembioml-0.1.0.dist-info/WHEEL
chembioml-0.1.0.dist-info/entry_points.txt
chembioml-0.1.0.dist-info/top_level.txt
chembioml-0.1.0.dist-info/RECORD
